{
  "Candidate": "lc_GRB260618B_cand28113",
  "Event": "GRB260618B",
  "Detector": "Sector 105 Cam 2 CCD 4",
  "Status": "FLAG",
  "Detection class": "none",
  "Detection count": 0,
  "RMS": 2.288534108992906,
  "Unflagged negative flux points": 127,
  "Trigger time": "2026-06-18 16:52:47.749",
  "RA (deg)": 320.03138986609366,
  "Dec (deg)": -59.91512355385918,
  "Column": 1884.084421354913,
  "Row": 119.91609022067,
  "Galactic longitude (deg)": 335.2261570740391,
  "Galactic latitude (deg)": -41.614400150231525,
  "Data file": "./cam2_ccd4//lcGRB/lc_GRB260618B_cand28113"
}
