{
  "Candidate": "lc_GRB260701A_cand48016",
  "Event": "GRB260701A",
  "Detector": "Sector 105 Cam 1 CCD 3",
  "Status": "FLAG",
  "Detection class": "none",
  "Detection count": 0,
  "RMS": 8.979658952566725,
  "Unflagged negative flux points": 5598,
  "Trigger time": "2026-07-01 02:14:24.147",
  "RA (deg)": 305.9333765587558,
  "Dec (deg)": -34.43957677202097,
  "Column": 706.600829596919,
  "Row": 914.9339650753843,
  "Galactic longitude (deg)": 7.800102374494736,
  "Galactic latitude (deg)": -33.061638296218156,
  "Data file": "./cam1_ccd3//lcGRB/lc_GRB260701A_cand48016"
}
