{
  "Candidate": "lc_GRB260618B_cand16074",
  "Event": "GRB260618B",
  "Detector": "Sector 105 Cam 2 CCD 2",
  "Status": "FLAG",
  "Detection class": "none",
  "Detection count": 0,
  "RMS": 3.6685500949158856,
  "Unflagged negative flux points": 5805,
  "Trigger time": "2026-06-18 16:52:47.749",
  "RA (deg)": 354.8941755328957,
  "Dec (deg)": -48.32486592405218,
  "Column": 509.03749992569107,
  "Row": 817.2940419657482,
  "Galactic longitude (deg)": 331.51909171976814,
  "Galactic latitude (deg)": -64.6210825329154,
  "Data file": "./cam2_ccd2//lcGRB/lc_GRB260618B_cand16074"
}
