{
  "Candidate": "lc_GRB260623A_cand22881",
  "Event": "GRB260623A",
  "Detector": "Sector 105 Cam 4 CCD 3",
  "Status": "FLAG",
  "Detection class": "none",
  "Detection count": 0,
  "RMS": 10.676256176560056,
  "Unflagged negative flux points": 5075,
  "Trigger time": "2026-06-23 12:54:34.874",
  "RA (deg)": 51.543855159399826,
  "Dec (deg)": -30.967690603040726,
  "Column": 1780.2780273358167,
  "Row": 1269.8436497213943,
  "Galactic longitude (deg)": 228.83956449467325,
  "Galactic latitude (deg)": -56.132263847274935,
  "Data file": "./cam4_ccd3//lcGRB/lc_GRB260623A_cand22881"
}
