{
  "Candidate": "lc_GRB260618B_cand22267",
  "Event": "GRB260618B",
  "Detector": "Sector 105 Cam 2 CCD 3",
  "Status": "FLAG",
  "Detection class": "none",
  "Detection count": 0,
  "RMS": 6.593144887337108,
  "Unflagged negative flux points": 5272,
  "Trigger time": "2026-06-18 16:52:47.749",
  "RA (deg)": 329.0801440189462,
  "Dec (deg)": -47.524820647293325,
  "Column": 1665.2926861949984,
  "Row": 410.3975868215815,
  "Galactic longitude (deg)": 350.0348208344537,
  "Galactic latitude (deg)": -50.375040438260775,
  "Data file": "./cam2_ccd3//lcGRB/lc_GRB260618B_cand22267"
}
