{
  "Candidate": "lc_GRB260618B_cand18907",
  "Event": "GRB260618B",
  "Detector": "Sector 105 Cam 3 CCD 2",
  "Status": "FLAG",
  "Detection class": "none",
  "Detection count": 0,
  "RMS": 6.729007361037086,
  "Unflagged negative flux points": 4215,
  "Trigger time": "2026-06-18 16:52:47.749",
  "RA (deg)": 15.472649481002954,
  "Dec (deg)": -53.847609207462064,
  "Column": 937.2361556690431,
  "Row": 1154.054467811495,
  "Galactic longitude (deg)": 299.51064501042225,
  "Galactic latitude (deg)": -63.21115138964807,
  "Data file": "./cam3_ccd2//lcGRB/lc_GRB260618B_cand18907"
}
