{
  "Candidate": "lc_GRB260618B_cand27594",
  "Event": "GRB260618B",
  "Detector": "Sector 105 Cam 2 CCD 4",
  "Status": "FLAG",
  "Detection class": "none",
  "Detection count": 0,
  "RMS": NaN,
  "Unflagged negative flux points": 8092,
  "Trigger time": "2026-06-18 16:52:47.749",
  "RA (deg)": 335.78442898678793,
  "Dec (deg)": -62.58929901430535,
  "Column": 1946.5774596272727,
  "Row": 1564.7824688008805,
  "Galactic longitude (deg)": 326.95829387705544,
  "Galactic latitude (deg)": -47.02774005313642,
  "Data file": "./cam2_ccd4//lcGRB/lc_GRB260618B_cand27594"
}
