{
  "Candidate": "lc_GRB260701A_cand30711",
  "Event": "GRB260701A",
  "Detector": "Sector 105 Cam 1 CCD 2",
  "Status": "FLAG",
  "Detection class": "none",
  "Detection count": 0,
  "RMS": 4.948866829705062,
  "Unflagged negative flux points": 3994,
  "Trigger time": "2026-07-01 02:14:24.147",
  "RA (deg)": 320.76318113066964,
  "Dec (deg)": -44.67240543896513,
  "Column": 668.0044904969834,
  "Row": 746.0821803920601,
  "Galactic longitude (deg)": 355.6939758700654,
  "Galactic latitude (deg)": -45.185838669656135,
  "Data file": "./cam1_ccd2//lcGRB/lc_GRB260701A_cand30711"
}
